dc_kafka_python_six_fix/__init__.py
dc_kafka_python_six_fix/fix.py
dc_kafka_python_six_fix-0.1.4.dist-info/LICENSE.txt
dc_kafka_python_six_fix-0.1.4.dist-info/METADATA
dc_kafka_python_six_fix-0.1.4.dist-info/WHEEL
dc_kafka_python_six_fix-0.1.4.dist-info/top_level.txt
dc_kafka_python_six_fix-0.1.4.dist-info/RECORD
