Metadata-Version: 2.2
Name: dc-kafka-python-six-fix
Version: 0.1.4
Summary: Fix for kafka-python 2.0.2 missing six module
Author-email: Denise Case <denisecase@gmail.com>
License: Apache-2.0
Project-URL: Homepage, https://github.com/denisecase/dc-kafka-python-six-fix
Project-URL: Repository, https://github.com/denisecase/dc-kafka-python-six-fix
Project-URL: BugTracker, https://github.com/denisecase/dc-kafka-python-six-fix/issues
Keywords: kafka,python,six,error,fix
Classifier: Intended Audience :: Developers
Classifier: License :: OSI Approved :: Apache Software License
Classifier: Programming Language :: Python :: 3.11
Requires-Python: >=3.11
License-File: LICENSE.txt
Requires-Dist: six==1.16.0
Requires-Dist: kafka-python==2.0.2
Provides-Extra: dev
Requires-Dist: pytest; extra == "dev"
